{"version":"1.0","unit":"","boxTypes":[{"id":1,"length":109,"width":80,"height":68,"lengthFlag":1,"widthFlag":1,"heightFlag":1,"total":1},{"id":2,"length":90,"width":45,"height":31,"lengthFlag":1,"widthFlag":1,"heightFlag":1,"total":2},{"id":3,"length":66,"width":56,"height":34,"lengthFlag":1,"widthFlag":1,"heightFlag":1,"total":2},{"id":4,"length":76,"width":66,"height":34,"lengthFlag":1,"widthFlag":1,"heightFlag":1,"total":1},{"id":5,"length":111,"width":80,"height":53,"lengthFlag":1,"widthFlag":1,"heightFlag":1,"total":1},{"id":6,"length":86,"width":59,"height":29,"lengthFlag":1,"widthFlag":1,"heightFlag":1,"total":2},{"id":7,"length":80,"width":72,"height":63,"lengthFlag":1,"widthFlag":1,"heightFlag":1,"total":2},{"id":8,"length":81,"width":47,"height":22,"lengthFlag":1,"widthFlag":1,"heightFlag":1,"total":2},{"id":9,"length":114,"width":80,"height":64,"lengthFlag":1,"widthFlag":1,"heightFlag":1,"total":1},{"id":10,"length":90,"width":37,"height":32,"lengthFlag":1,"widthFlag":1,"heightFlag":1,"total":2},{"id":11,"length":75,"width":48,"height":40,"lengthFlag":1,"widthFlag":1,"heightFlag":1,"total":2},{"id":12,"length":67,"width":52,"height":45,"lengthFlag":1,"widthFlag":1,"heightFlag":1,"total":2}],"list":[{"boxes":[{"id":1,"x":0,"y":0,"z":0,"length":80,"width":68,"height":109},{"id":4,"x":0,"y":0,"z":109,"length":76,"width":66,"height":34},{"id":11,"x":0,"y":73,"z":0,"length":40,"width":48,"height":75},{"id":11,"x":40,"y":73,"z":0,"length":40,"width":48,"height":75},{"id":12,"x":0,"y":76,"z":75,"length":52,"width":45,"height":67},{"id":8,"x":52,"y":74,"z":75,"length":22,"width":47,"height":81},{"id":7,"x":80,"y":0,"z":0,"length":80,"width":63,"height":72},{"id":7,"x":80,"y":0,"z":72,"length":80,"width":63,"height":72},{"id":6,"x":80,"y":63,"z":0,"length":86,"width":29,"height":59},{"id":6,"x":80,"y":92,"z":0,"length":86,"width":29,"height":59},{"id":2,"x":80,"y":76,"z":59,"length":31,"width":45,"height":90},{"id":2,"x":111,"y":76,"z":59,"length":31,"width":45,"height":90},{"id":9,"x":166,"y":0,"z":0,"length":114,"width":64,"height":80},{"id":5,"x":166,"y":64,"z":0,"length":111,"width":53,"height":80},{"id":10,"x":166,"y":0,"z":80,"length":32,"width":90,"height":37},{"id":10,"x":166,"y":0,"z":117,"length":32,"width":90,"height":37},{"id":8,"x":203,"y":70,"z":80,"length":22,"width":47,"height":81},{"id":3,"x":211,"y":0,"z":80,"length":66,"width":34,"height":56},{"id":3,"x":211,"y":34,"z":80,"length":66,"width":34,"height":56},{"id":12,"x":225,"y":72,"z":80,"length":52,"width":45,"height":67}],"container":{"length":280,"width":121,"height":161,"volume":5454680.0},"utilization":0.792437319879443}]}
