{"version":"1.0","unit":"","boxTypes":[{"id":1,"length":73,"width":73,"height":36,"lengthFlag":1,"widthFlag":1,"heightFlag":1,"total":16}],"list":[{"boxes":[{"id":1,"x":0,"y":0,"z":0,"length":36,"width":73,"height":73},{"id":1,"x":36,"y":0,"z":0,"length":73,"width":36,"height":73},{"id":1,"x":36,"y":36,"z":0,"length":73,"width":36,"height":73},{"id":1,"x":36,"y":72,"z":0,"length":73,"width":36,"height":73},{"id":1,"x":36,"y":0,"z":73,"length":73,"width":73,"height":36},{"id":1,"x":36,"y":0,"z":109,"length":73,"width":73,"height":36},{"id":1,"x":109,"y":0,"z":0,"length":73,"width":36,"height":73},{"id":1,"x":109,"y":36,"z":0,"length":73,"width":36,"height":73},{"id":1,"x":109,"y":72,"z":0,"length":73,"width":36,"height":73},{"id":1,"x":109,"y":0,"z":73,"length":73,"width":73,"height":36},{"id":1,"x":109,"y":0,"z":109,"length":73,"width":73,"height":36},{"id":1,"x":182,"y":0,"z":0,"length":73,"width":36,"height":73},{"id":1,"x":182,"y":36,"z":0,"length":73,"width":36,"height":73},{"id":1,"x":182,"y":72,"z":0,"length":73,"width":36,"height":73},{"id":1,"x":182,"y":0,"z":73,"length":73,"width":73,"height":36},{"id":1,"x":182,"y":0,"z":109,"length":73,"width":73,"height":36}],"container":{"length":255,"width":108,"height":145,"volume":3993300.0},"utilization":0.7686635113815641}]}
