{"version":"1.0","unit":"","boxTypes":[{"id":1,"length":84,"width":81,"height":23,"lengthFlag":1,"widthFlag":1,"heightFlag":1,"total":5},{"id":2,"length":115,"width":72,"height":64,"lengthFlag":1,"widthFlag":1,"heightFlag":1,"total":3},{"id":3,"length":77,"width":49,"height":25,"lengthFlag":1,"widthFlag":1,"heightFlag":1,"total":4}],"list":[{"boxes":[{"id":1,"x":0,"y":0,"z":0,"length":81,"width":84,"height":23},{"id":1,"x":0,"y":0,"z":23,"length":81,"width":84,"height":23},{"id":1,"x":0,"y":0,"z":46,"length":81,"width":84,"height":23},{"id":1,"x":0,"y":0,"z":69,"length":81,"width":84,"height":23},{"id":1,"x":0,"y":0,"z":92,"length":81,"width":84,"height":23},{"id":3,"x":81,"y":0,"z":0,"length":49,"width":77,"height":25},{"id":3,"x":130,"y":0,"z":0,"length":49,"width":77,"height":25},{"id":2,"x":81,"y":0,"z":25,"length":64,"width":72,"height":115},{"id":3,"x":179,"y":0,"z":0,"length":49,"width":77,"height":25},{"id":2,"x":145,"y":0,"z":25,"length":64,"width":72,"height":115},{"id":3,"x":228,"y":0,"z":0,"length":49,"width":77,"height":25},{"id":2,"x":209,"y":0,"z":25,"length":64,"width":72,"height":115}],"container":{"length":277,"width":84,"height":140,"volume":3257520.0},"utilization":0.8440531447235935}]}
