{"version":"1.0","unit":"","boxTypes":[{"id":1,"length":114,"width":67,"height":25,"lengthFlag":1,"widthFlag":1,"heightFlag":1,"total":6},{"id":2,"length":92,"width":79,"height":25,"lengthFlag":1,"widthFlag":1,"heightFlag":1,"total":4},{"id":3,"length":89,"width":87,"height":36,"lengthFlag":1,"widthFlag":1,"heightFlag":1,"total":4}],"list":[{"boxes":[{"id":3,"x":0,"y":0,"z":0,"length":87,"width":89,"height":36},{"id":3,"x":0,"y":0,"z":36,"length":87,"width":89,"height":36},{"id":3,"x":0,"y":0,"z":72,"length":87,"width":89,"height":36},{"id":3,"x":0,"y":0,"z":108,"length":87,"width":89,"height":36},{"id":2,"x":87,"y":0,"z":0,"length":92,"width":79,"height":25},{"id":1,"x":87,"y":0,"z":25,"length":67,"width":25,"height":114},{"id":1,"x":87,"y":25,"z":25,"length":67,"width":25,"height":114},{"id":1,"x":87,"y":50,"z":25,"length":67,"width":25,"height":114},{"id":2,"x":179,"y":0,"z":0,"length":92,"width":79,"height":25},{"id":1,"x":154,"y":0,"z":25,"length":67,"width":25,"height":114},{"id":1,"x":154,"y":25,"z":25,"length":67,"width":25,"height":114},{"id":1,"x":154,"y":50,"z":25,"length":67,"width":25,"height":114},{"id":2,"x":221,"y":0,"z":25,"length":25,"width":79,"height":92},{"id":2,"x":246,"y":0,"z":25,"length":25,"width":79,"height":92}],"container":{"length":271,"width":89,"height":144,"volume":3473136.0},"utilization":0.8601713264323655}]}
